pylifemap/__init__.py
pylifemap/data/__init__.py
pylifemap/data/aggregation.py
pylifemap/data/backend_data.py
pylifemap/data/check_taxids.py
pylifemap/data/lazy_loading.py
pylifemap/data/lifemap_data.py
pylifemap/data/serialization.py
pylifemap/layers/__init__.py
pylifemap/layers/base.py
pylifemap/layers/layer_donuts.py
pylifemap/layers/layer_heatmap.py
pylifemap/layers/layer_heatmap_deck.py
pylifemap/layers/layer_icons.py
pylifemap/layers/layer_lines.py
pylifemap/layers/layer_points.py
pylifemap/layers/layer_screengrid.py
pylifemap/layers/layer_text.py
pylifemap/lifemap.py
pylifemap/static/deck/widget.css
pylifemap/static/deck/widget.js
pylifemap/static/nodeck/widget.css
pylifemap/static/nodeck/widget.js
pylifemap/utils.py
pylifemap/widget.py
pylifemap-0.1.dist-info/WHEEL
pylifemap-0.1.dist-info/METADATA
pylifemap-0.1.dist-info/RECORD
