Metadata-Version: 2.3
Name: pylifemap
Version: 0.1
Summary: Python package for Lifemap visualizations
Keywords: 
Author: Julien Barnier, Damien de Vienne
Author-email: Julien Barnier <julien.barnier@cnrs.fr>, Damien de Vienne <damien.de-vienne@cnrs.fr>
License: MIT License
Classifier: Development Status :: 4 - Beta
Classifier: Programming Language :: Python
Requires-Dist: anywidget[dev]>=0.9.21
Requires-Dist: ipywidgets>=8.1.7
Requires-Dist: pandas>=2.0.0
Requires-Dist: platformdirs>=4.3.6
Requires-Dist: polars>=1.17.0
Requires-Dist: pyarrow>=22.0.0
Requires-Dist: requests>=2.32.3
Requires-Python: >=3.10
Project-URL: Documentation, https://github.com/Lifemap-ToL/pylifemap#readme
Project-URL: Issues, https://github.com/Lifemap-ToL/pylifemap/issues
Project-URL: Source, https://github.com/Lifemap-ToL/pylifemap
